timera/__init__.py
timera/collector.py
timera/db.py
timera/main.py
timera/threadio.py
timera/util.py
timera/exc/__init__.py
timera/exc/exc.py
timera/plugins/__init__.py
timera/plugins/httptimer/__init__.py
timera/plugins/httptimer/httptimer.py
timera-0.2.1.dist-info/DESCRIPTION.rst
timera-0.2.1.dist-info/LICENSE.txt
timera-0.2.1.dist-info/METADATA
timera-0.2.1.dist-info/RECORD
timera-0.2.1.dist-info/WHEEL
timera-0.2.1.dist-info/entry_points.txt
timera-0.2.1.dist-info/metadata.json
timera-0.2.1.dist-info/top_level.txt
