Metadata-Version: 2.0
Name: timera
Version: 0.2.1
Summary: Store metrics in InfluxDB.
Home-page: https://github.com/natej/timera
Author: Nathan Jennings
Author-email: natej.git@gmail.com
License: This is the MIT License: https://opensource.org/licenses/MIT
Requires-Dist: influxdb (>=4.1.0)
Requires-Dist: requests (>=2.15.0)
